cfl_common/__init__.py
cfl_common/setup.py
cfl_common/common/__init__.py
cfl_common/common/app_settings.py
cfl_common/common/apps.py
cfl_common/common/context_processors.py
cfl_common/common/csp_config.py
cfl_common/common/mail.py
cfl_common/common/models.py
cfl_common/common/permissions.py
cfl_common/common/utils.py
cfl_common/common/helpers/__init__.py
cfl_common/common/helpers/data_migration_loader.py
cfl_common/common/helpers/emails.py
cfl_common/common/helpers/generators.py
cfl_common/common/helpers/organisation.py
cfl_common/common/migrations/0001_initial.py
cfl_common/common/migrations/0002_emailverification.py
cfl_common/common/migrations/0003_aimmocharacter.py
cfl_common/common/migrations/0004_add_aimmocharacters.py
cfl_common/common/migrations/0005_add_worksheets.py
cfl_common/common/migrations/0006_update_aimmo_character_image_path.py
cfl_common/common/migrations/0007_add_pdf_names_to_first_two_worksheets.py
cfl_common/common/migrations/0008_unlock_worksheet_3.py
cfl_common/common/migrations/0009_add_blocked_time_to_teacher_and_student.py
cfl_common/common/migrations/0010_remove_teacher_title.py
cfl_common/common/migrations/0011_student_login_id.py
cfl_common/common/migrations/0012_usersession.py
cfl_common/common/migrations/0013_class_school.py
cfl_common/common/migrations/0014_login_type.py
cfl_common/common/migrations/0015_dailyactivity.py
cfl_common/common/migrations/0016_joinreleasestudent.py
cfl_common/common/migrations/0017_copy_email_to_username.py
cfl_common/common/migrations/0018_update_aimmo_character_image_path.py
cfl_common/common/migrations/0019_aimmocharacter_alt.py
cfl_common/common/migrations/0020_class_is_active_and_null_access_code.py
cfl_common/common/migrations/0021_school_is_active.py
cfl_common/common/migrations/0022_school_cleanup.py
cfl_common/common/migrations/0023_userprofile_aimmo_badges.py
cfl_common/common/migrations/0024_teacher_invited_by.py
cfl_common/common/migrations/0025_schoolteacherinvitation.py
codeforlife_portal-8.9.14.dist-info/licenses/LICENSE.md
codeforlife_portal-8.9.14.dist-info/METADATA
codeforlife_portal-8.9.14.dist-info/WHEEL
codeforlife_portal-8.9.14.dist-info/top_level.txt
codeforlife_portal-8.9.14.dist-info/RECORD
